setup.py
hello_world_diy.egg-info/PKG-INFO
hello_world_diy.egg-info/SOURCES.txt
hello_world_diy.egg-info/dependency_links.txt
hello_world_diy.egg-info/top_level.txt
src/__init__.py
src/hello_utils.py