Metadata-Version: 1.0
Name: hello-world-diy
Version: 0.0.1
Summary: hello world diy
Home-page: UNKNOWN
Author: Happy Puppy
Author-email: UNKNOWN
License: UNKNOWN
Platform: UNKNOWN
